mypy_zope/__init__.py
mypy_zope/plugin.py
zope-stubs/__init__.pyi
zope-stubs/interface/__init__.pyi
zope-stubs/interface/_compat.pyi
zope-stubs/interface/_flatten.pyi
zope-stubs/interface/_zope_interface_coptimizations.pyi
zope-stubs/interface/adapter.pyi
zope-stubs/interface/advice.pyi
zope-stubs/interface/declarations.pyi
zope-stubs/interface/document.pyi
zope-stubs/interface/exceptions.pyi
zope-stubs/interface/interface.pyi
zope-stubs/interface/interfaces.pyi
zope-stubs/interface/registry.pyi
zope-stubs/interface/ro.pyi
zope-stubs/interface/verify.pyi
zope-stubs/interface/common/__init__.pyi
zope-stubs/interface/common/idatetime.pyi
zope-stubs/interface/common/interfaces.pyi
zope-stubs/interface/common/mapping.pyi
zope-stubs/interface/common/sequence.pyi
zope-stubs/schema/__init__.pyi
zope-stubs/schema/_bootstrapfields.pyi
zope-stubs/schema/_bootstrapinterfaces.pyi
zope-stubs/schema/_compat.pyi
zope-stubs/schema/_field.pyi
zope-stubs/schema/_messageid.pyi
zope-stubs/schema/_schema.pyi
zope-stubs/schema/accessors.pyi
zope-stubs/schema/fieldproperty.pyi
zope-stubs/schema/interfaces.pyi
zope-stubs/schema/vocabulary.pyi
mypy_zope-1.0.12.dist-info/LICENSE
mypy_zope-1.0.12.dist-info/METADATA
mypy_zope-1.0.12.dist-info/WHEEL
mypy_zope-1.0.12.dist-info/top_level.txt
mypy_zope-1.0.12.dist-info/RECORD
