Metadata-Version: 2.1
Name: mypy-zope
Version: 1.0.12
Summary: Plugin for mypy to support zope interfaces
Home-page: https://github.com/Shoobx/mypy-zope
Author: Andrey Lebedev
Author-email: andrey.lebedev@gmail.com
Keywords: mypy,zope,interfaces,typing
Classifier: Development Status :: 5 - Production/Stable
Classifier: Environment :: Console
Classifier: Intended Audience :: Developers
Classifier: Programming Language :: Python :: 3
Classifier: Programming Language :: Python :: 3.8
Classifier: Programming Language :: Python :: 3.9
Classifier: Programming Language :: Python :: 3.10
Classifier: Programming Language :: Python :: 3.11
Classifier: Programming Language :: Python :: 3.12
Classifier: Programming Language :: Python :: 3.13
Classifier: License :: OSI Approved :: MIT License
Classifier: Operating System :: OS Independent
Classifier: Topic :: Software Development
License-File: LICENSE
Requires-Dist: mypy<1.17.0,>=1.0.0
Requires-Dist: zope.interface
Requires-Dist: zope.schema
Provides-Extra: test
Requires-Dist: pytest>=4.6; extra == "test"
Requires-Dist: pytest-cov; extra == "test"
Requires-Dist: lxml; extra == "test"
